wcon/__init__.py
wcon/measurement_unit.py
wcon/version.py
wcon/wcon_data.py
wcon/wcon_parser.py
wcon-1.1.0.dist-info/DESCRIPTION.rst
wcon-1.1.0.dist-info/METADATA
wcon-1.1.0.dist-info/RECORD
wcon-1.1.0.dist-info/WHEEL
wcon-1.1.0.dist-info/metadata.json
wcon-1.1.0.dist-info/top_level.txt
