Metadata-Version: 2.0
Name: wcon
Version: 1.1.0
Summary: Worm tracker Commons Object Notation
Home-page: https://github.com/openworm/tracker-commons
Author: Kerr, R; Brown, A; Currie, M; OpenWorm
Author-email: ichoran@gmail.com
License: MIT
Keywords: C. elegans worm tracking
Platform: UNKNOWN
Classifier: Development Status :: 4 - Beta
Classifier: Intended Audience :: Science/Research
Classifier: Topic :: Scientific/Engineering :: Bio-Informatics
Classifier: License :: OSI Approved :: MIT License
Classifier: Programming Language :: Python :: 2
Classifier: Programming Language :: Python :: 2.7
Classifier: Programming Language :: Python :: 3
Classifier: Programming Language :: Python :: 3.4
Classifier: Programming Language :: Python :: 3.5
Requires-Dist: jsonschema
